{
	"thislanguage": ["Ukraine", "Українська"],
	"lang": "Мова",
	
	"free": "MoonBrawl - Безкоштовний сервер! Тут немає жодних платних функцій!"
	"link": "Привіт, схоже в тебе багато кубків, і ти <c7>не прив'язав свій аккаунт!</c>\n\nПрив'язавши акаунт до Telegram боту, ти застережеш себе від взлому, зможешь перенести свій аккаунт у разі його втрати.\n\n<c2>Наполегливо рекомендуємо прив'язати аккаунт до боту:</c> ",
	"linkprocess": "Для підтвердженя прив'язки до Telegram'у аккаунту з ніком {} будь ласка введіть цей код: {}",
	"tg": "Телеграм",
	"ds": "Дискорд",
	"selfdata": "Ваш токен: {}\n\nНавіщо потрібні ці данні?: Ці токени потрібні для прив'язки вашого аккаунту до TG боту\n<c2>НІКОМУ ЇХ НЕ ПЕРЕДАВАЙТЕ!</c>",
	
	"help": "/help - цей список\n/theme <id> - змінити тему\n/lang <cc> - змінити мову",
	"availablelang": "Список доступних мов:\n\n",
	"koshka_negr": "Невідома команда",
	"theme": "Не вказаний ID фону! Фон встановлюється командой /theme [id]! Список ID:",
	"rejoin": "Готово! Перезайди в MB.",
	"report": ["Скарга відправлена!", "Не вдалося відправити скаргу"],
	
	"promo": ["А ти знав що в нас є Telegram-канал?", "У нас ти можеш знайти самі свіжі новини про сервер!", "Перейти"],
	
	"gift": ["Подарунок", "Подарунки"],
	
	"second": ["Секунда", "Секунд", "Секунди"],
	"minute": ["Хвилина", "Хвилин", "Хвилини"],
	"hour": ["Година", "Годин", "Години"],
	"day": ["День", "Днів", "Дні"],
	
	"state": ["Вимкнути", "Увімкнути"]
	"staterizator0": ["Вимкнено", "Вимкнули", "Вимкнено", "Вимкнені"],  
	"staterizator1": ["Увімкнено", "Увімкнули", "Увімкнений", "Увімкнені"],  
	
	"gems": "Геми",
	"coins": "Монети",
	"starpoint": "Старпоїнти",
	
	"smallbox": ["Маленький ящик", "Маленькі ящики", "Маленьких ящиків"],
	"box": ["Середній ящик", "Середні ящики", "Середніх ящиків"],
	"megabox": ["Мегаящик", "Мегаящики", "Мегаящиків"],
	
	
	
	"missing": "Видалений аккаунт",
	"update": "Вишло оновлення! Встановіть оновлення на цьому сайті: ",
	"account": "Ваш аккаунт не знайдено в базі даних. Будь ласка, очістіть дані MoonBrawl в налаштуваннях або переустановіть MoonBrawl.",
	"whitelist": "Вашого IP в Whitelist немає! Вимкніть Whitelist через @moonbrawlbot",
	"banned": "😕 Ви були заблоковані в MB!\nЧас до разбану: {}.\nПричина: {}",
        "corrupted": "Seems your account is corrupted.",
	
	"bughunter_about": "Знаходьте баги в MB та отримуйте за це винагороди у вигляді мегаящиків, гемів и т.п.!",
	"bughunter_catch": "Ви піймали баг (ID: {}). Надішліть його через команду /hunter <ID>\nІ отримайте винагороду!",
	"bughunter_available": "Ви отримали винагороду {} {} за баг (ID: {}), заберіть його!",
	
	
	
	"_comment": "Не потрібно переводити те що снизу.",
	
	"yn": "(Y/n) > ",
	"l": "\n"
	"debug": "",
	"hi": "Welcome to MBCLI.\n",
	"bye": "Bye.\n",
	"flush": "",
	"terminate": "Terminate? ",
	"ebalo": ["tcp", "udp"],
	"db_upala": "Timeout! Database not respond within {}ms.",
	"corepizdit": "Core napizdel (#{}:#{})",
	"ionaebal": "IO Error",
	"zaebal": "Potential data loss detected. Try to go naxui or restart moondb",
	"sectorcorrupted": "Sector corrupted (#{}, B{}). fill with zeros?",
	"blya": "Unpaired bits",
	"da_ne_nado_mne_tyt": "",
	"sychki": "Технологии пидерастов блять заебали уже со своими технологиями записи битов по головке жёсткого диска. Лучше по головке члена запиши себе блять нолик"
}
